phlearn/__init__.py
phlearn/control/__init__.py
phlearn/control/casadiNN.py
phlearn/control/casadiPH.py
phlearn/control/mpc.py
phlearn/control/phcontroller.py
phlearn/control/pid.py
phlearn/control/reference.py
phlearn/phnns/__init__.py
phlearn/phnns/conservative_dissipative_neural_network.py
phlearn/phnns/dynamic_system_neural_network.py
phlearn/phnns/models.py
phlearn/phnns/ode_models.py
phlearn/phnns/pde_models.py
phlearn/phnns/pseudo_hamiltonian_neural_network.py
phlearn/phnns/pseudo_hamiltonian_pde_neural_network.py
phlearn/phnns/train_utils.py
phlearn/phnns/tests/__init__.py
phlearn/phnns/tests/test_phnns.py
phlearn/phsystems/__init__.py
phlearn/phsystems/allen_cahn_system.py
phlearn/phsystems/bbm_system.py
phlearn/phsystems/burgers_system.py
phlearn/phsystems/cahn_hilliard_system.py
phlearn/phsystems/conservative_dissipative_system.py
phlearn/phsystems/fvm.py
phlearn/phsystems/heat_system.py
phlearn/phsystems/kdv_system.py
phlearn/phsystems/msd_system.py
phlearn/phsystems/perona_malik_system.py
phlearn/phsystems/phase_system.py
phlearn/phsystems/pseudo_Hamiltonian_system.py
phlearn/phsystems/tank_system.py
phlearn/phsystems/ode/__init__.py
phlearn/phsystems/ode/msd_system.py
phlearn/phsystems/ode/pseudo_hamiltonian_system.py
phlearn/phsystems/ode/tank_system.py
phlearn/phsystems/ode/tests/__init__.py
phlearn/phsystems/ode/tests/test_phsystems.py
phlearn/phsystems/pde/__init__.py
phlearn/phsystems/pde/allen_cahn_system.py
phlearn/phsystems/pde/bbm_system.py
phlearn/phsystems/pde/cahn_hilliard_system.py
phlearn/phsystems/pde/heat_system.py
phlearn/phsystems/pde/kdv_system.py
phlearn/phsystems/pde/perona_malik_system.py
phlearn/phsystems/pde/pseudo_hamiltonian_pde_system.py
phlearn/phsystems/tests/__init__.py
phlearn/phsystems/tests/test_phsystems.py
phlearn/utils/__init__.py
phlearn/utils/derivatives.py
phlearn/utils/utils.py
phlearn-1.1.2.dist-info/LICENSE.txt
phlearn-1.1.2.dist-info/METADATA
phlearn-1.1.2.dist-info/WHEEL
phlearn-1.1.2.dist-info/top_level.txt
phlearn-1.1.2.dist-info/RECORD
