Metadata-Version: 2.1
Name: phlearn
Version: 1.1.2
Summary: A package for simulating and learning pseudo-Hamiltonian systems. For further details, see https://arxiv.org/pdf/2206.02660.pdf and https://arxiv.org/abs/2304.14374
Home-page: https://github.com/SINTEF/pseudo-hamiltonian-neural-networks
Author: Sølve Eidnes
Author-email: solve.eidnes@sintef.no
License: MIT
Keywords: pseudo-Hamiltonian neural networks
Classifier: Development Status :: 5 - Production/Stable
License-File: LICENSE.txt
Requires-Dist: networkx (>=2.7.1)
Requires-Dist: numpy (>=1.22.3)
Requires-Dist: torchvision
Requires-Dist: scipy (>=1.8.0)
Requires-Dist: torch
Requires-Dist: torchaudio
Requires-Dist: matplotlib
Requires-Dist: imageio
Requires-Dist: tqdm
Requires-Dist: autograd
Requires-Dist: IPython
Provides-Extra: control
Requires-Dist: casadi ; extra == 'control'
Requires-Dist: do-mpc ; extra == 'control'
